Metadata-Version: 1.1
Name: advanced-calculator
Version: 0.0.3
Summary: a calculator with some advanced functions
Home-page: UNKNOWN
Author: Skylar Kerzner
Author-email: skylar.kerzner@gmail.com
License: MIT
Platform: UNKNOWN
Classifier: Development Status :: 5 - Production/Stable
Classifier: Intended Audience :: Education
Classifier: Operating System :: MacOS
Classifier: License :: OSI Approved :: MIT License
Classifier: Programming Language :: Python :: 3
